{
  "bear": {
    "n": 5940,
    "ics": {
      "feat_eye": -0.0447,
      "feat_ear": -0.0399,
      "feat_nose": -0.0267,
      "feat_tongue": -0.0665,
      "feat_body": 0.031,
      "feat_pulse": -0.026,
      "feat_aura": -0.034,
      "feat_mind": -0.035
    },
    "passed": 1,
    "diagnostics": {
      "feat_eye": "ok",
      "feat_ear": "ok",
      "feat_nose": "ok",
      "feat_tongue": "ok",
      "feat_body": "ok",
      "feat_pulse": "ok",
      "feat_aura": "ok",
      "feat_mind": "ok"
    }
  },
  "bull": {
    "n": 4774,
    "ics": {
      "feat_eye": 0.0574,
      "feat_ear": 0.0292,
      "feat_nose": 0.0077,
      "feat_tongue": -0.0097,
      "feat_body": 0.0381,
      "feat_pulse": 0.006,
      "feat_aura": -0.0026,
      "feat_mind": -0.0174
    },
    "passed": 1,
    "diagnostics": {
      "feat_eye": "ok",
      "feat_ear": "ok",
      "feat_nose": "ok",
      "feat_tongue": "ok",
      "feat_body": "ok",
      "feat_pulse": "ok",
      "feat_aura": "ok",
      "feat_mind": "ok"
    }
  },
  "chop": {
    "n": 11818,
    "ics": {
      "feat_eye": -0.0376,
      "feat_ear": -0.0069,
      "feat_nose": 0.0879,
      "feat_tongue": -0.1698,
      "feat_body": -0.0019,
      "feat_pulse": 0.1977,
      "feat_aura": -0.0779,
      "feat_mind": -0.0884
    },
    "passed": 5,
    "diagnostics": {
      "feat_eye": "ok",
      "feat_ear": "ok",
      "feat_nose": "ok",
      "feat_tongue": "ok",
      "feat_body": "ok",
      "feat_pulse": "ok",
      "feat_aura": "ok",
      "feat_mind": "ok"
    }
  },
  "neutral": {
    "n": 21,
    "ics": {
      "feat_eye": 0.2922,
      "feat_ear": 0.1573,
      "feat_nose": -0.0954,
      "feat_tongue": 0.0786,
      "feat_body": 0.0,
      "feat_pulse": 0.0,
      "feat_aura": 0.0,
      "feat_mind": 0.0
    },
    "passed": 4,
    "diagnostics": {
      "feat_eye": "ok",
      "feat_ear": "ok",
      "feat_nose": "ok",
      "feat_tongue": "ok",
      "feat_body": "constant_feature",
      "feat_pulse": "too_few_samples",
      "feat_aura": "too_few_samples",
      "feat_mind": "too_few_samples"
    }
  },
  "overall_simulated_pyramid_win": 0.628,
  "overall_n": 22553,
  "regime_meta": {
    "method": "mind_tertiles_with_feature_regime_fallback",
    "p33": -0.006956,
    "p67": 0.014837,
    "fallback_rows": 8283,
    "mind_rows": 14270
  },
  "regime_counts": {
    "chop": 11818,
    "bull": 4774,
    "bear": 5940,
    "neutral": 21
  }
}